{
  "WorkItem": {
    "AffectedComponent": {
      "Name": "",
      "DisplayName": ""
    },
    "ClosedComment": "",
    "ClosedDate": null,
    "CommentCount": 0,
    "Custom": null,
    "Description": "I used HTML Agility pack to screen scrap a site with the login credentials but after the logging all I get is a message \"You have to login to access this page\".  Is this a security issue? or any other problem with screen scrap? Please help!!!",
    "LastUpdatedDate": "2016-06-10T12:46:00.763-07:00",
    "PlannedForRelease": "",
    "ReleaseVisibleToPublic": false,
    "Priority": {
      "Name": "Unassigned",
      "Severity": 0,
      "Id": 0
    },
    "ProjectName": "htmlagilitypack",
    "ReportedDate": "2016-06-07T13:08:33.347-07:00",
    "Status": {
      "Name": "Proposed",
      "Id": 1
    },
    "ReasonClosed": {
      "Name": "Unassigned"
    },
    "Summary": "HTML Agility Pack",
    "Type": {
      "Name": "Unassigned",
      "Id": 5
    },
    "VoteCount": 1,
    "Id": 43433
  },
  "FileAttachments": [],
  "Comments": []
}